{
    "function_name": "delete_all_collections",
    "docstring": null,
    "decorators": null,
    "parameters": null,
    "returns": "None",
    "is_method": true,
    "is_async": false,
    "id": "postcode:databases:arangodb:arangodb_connector.py__*__MODULE__*__CLASS-ArangoDBConnector__*__FUNCTION-delete_all_collections",
    "file_path": "postcode/databases/arangodb/arangodb_connector.py",
    "parent_id": "postcode:databases:arangodb:arangodb_connector.py__*__MODULE__*__CLASS-ArangoDBConnector",
    "block_type": "FUNCTION",
    "start_line_num": 78,
    "end_line_num": 86,
    "code_content": "\ndef delete_all_collections(self) -> None:\n    collections: Result[Jsons] = self.db.collections()\n\n    for collection in collections:  # type: ignore # FIXME: Fix type error\n        if not collection[\"name\"].startswith(\"_\"):  # Skip system collections\n            self.db.delete_collection(collection[\"name\"])\n            logging.info(f\"Deleted collection: {collection['name']}\")\n",
    "important_comments": [
        {
            "content": "# type: ignore # FIXME: Fix type error",
            "comment_types": [
                "FIXME"
            ]
        }
    ],
    "dependencies": null,
    "summary": null,
    "children_ids": []
}